wsection/GB-section.csv
wsection/GBSection.py
wsection/Section.py
wsection/W-section.csv
wsection/WSection.py
wsection/__init__.py
wsection-2.0.2.dist-info/LICENSE
wsection-2.0.2.dist-info/METADATA
wsection-2.0.2.dist-info/WHEEL
wsection-2.0.2.dist-info/top_level.txt
wsection-2.0.2.dist-info/RECORD
