Metadata-Version: 2.1
Name: wsection
Version: 2.0.2
Summary: A python package to get properties of W-shaped steel section
Author: Wenchen Lie
Author-email: 666@e.gzhu.edu.cn
License-File: LICENSE
Requires-Dist: pandas
